LearnopenglZhongwenJiaocheng/README.md
LearnopenglZhongwenJiaocheng/__init__.py
LearnopenglZhongwenJiaocheng/__main__.py
LearnopenglZhongwenJiaocheng/file.epub
LearnopenglZhongwenJiaocheng/index.html
LearnopenglZhongwenJiaocheng/css/__init__.py
LearnopenglZhongwenJiaocheng/css/annotations.css
LearnopenglZhongwenJiaocheng/css/main.css
LearnopenglZhongwenJiaocheng/css/normalize.css
LearnopenglZhongwenJiaocheng/css/popup.css
LearnopenglZhongwenJiaocheng/font/__init__.py
LearnopenglZhongwenJiaocheng/font/fontello.eot
LearnopenglZhongwenJiaocheng/font/fontello.svg
LearnopenglZhongwenJiaocheng/font/fontello.ttf
LearnopenglZhongwenJiaocheng/font/fontello.woff
LearnopenglZhongwenJiaocheng/img/__init__.py
LearnopenglZhongwenJiaocheng/img/annotator-glyph-sprite.png
LearnopenglZhongwenJiaocheng/img/annotator-icon-sprite.png
LearnopenglZhongwenJiaocheng/img/apple-touch-icon.png
LearnopenglZhongwenJiaocheng/img/cancelfullscreen.png
LearnopenglZhongwenJiaocheng/img/close.png
LearnopenglZhongwenJiaocheng/img/fullscreen.png
LearnopenglZhongwenJiaocheng/img/loader.gif
LearnopenglZhongwenJiaocheng/img/menu-icon.png
LearnopenglZhongwenJiaocheng/img/save.png
LearnopenglZhongwenJiaocheng/img/saved.png
LearnopenglZhongwenJiaocheng/img/settings-s.png
LearnopenglZhongwenJiaocheng/img/settings.png
LearnopenglZhongwenJiaocheng/img/star.png
LearnopenglZhongwenJiaocheng/js/__init__.py
LearnopenglZhongwenJiaocheng/js/epub.js
LearnopenglZhongwenJiaocheng/js/epub.min.js
LearnopenglZhongwenJiaocheng/js/epub.min.map
LearnopenglZhongwenJiaocheng/js/hooks.min.js
LearnopenglZhongwenJiaocheng/js/hooks.min.map
LearnopenglZhongwenJiaocheng/js/reader.js
LearnopenglZhongwenJiaocheng/js/reader.js.map
LearnopenglZhongwenJiaocheng/js/reader.min.js
LearnopenglZhongwenJiaocheng/js/reader.min.map
LearnopenglZhongwenJiaocheng/js/hooks/__init__.py
LearnopenglZhongwenJiaocheng/js/hooks/extensions/__init__.py
LearnopenglZhongwenJiaocheng/js/hooks/extensions/highlight.js
learnopengl_zhongwen_jiaocheng-2024.3.4.0.dist-info/METADATA
learnopengl_zhongwen_jiaocheng-2024.3.4.0.dist-info/WHEEL
learnopengl_zhongwen_jiaocheng-2024.3.4.0.dist-info/entry_points.txt
learnopengl_zhongwen_jiaocheng-2024.3.4.0.dist-info/top_level.txt
learnopengl_zhongwen_jiaocheng-2024.3.4.0.dist-info/RECORD
